coordinates2country/__init__.py
coordinates2country/coordinates2country.py
coordinates2country/resources/countries-8bitgray.png
coordinates2country/resources/countries.csv
tests/__init__.py
tests/test_coordinates2country.py
coordinates2country-1.0.8.dist-info/LICENSE
coordinates2country-1.0.8.dist-info/METADATA
coordinates2country-1.0.8.dist-info/WHEEL
coordinates2country-1.0.8.dist-info/top_level.txt
coordinates2country-1.0.8.dist-info/RECORD
