Metadata-Version: 2.2
Name: coordinates2country
Version: 1.0.8
Summary: Fast reverse geocoding without internet connection
Home-page: https://github.com/yourusername/coordinates2country-python
Author: Abram Astle
Author-email: castle676767@gmail.com
Classifier: Programming Language :: Python :: 3
Classifier: License :: OSI Approved :: Apache Software License
Classifier: Operating System :: OS Independent
Requires-Python: >=3.6
License-File: LICENSE
Requires-Dist: Pillow
Dynamic: author
Dynamic: author-email
Dynamic: classifier
Dynamic: description
Dynamic: description-content-type
Dynamic: home-page
Dynamic: requires-dist
Dynamic: requires-python
Dynamic: summary
